arcade_serve/__init__.py
arcade_serve/py.typed
arcade_serve/utils.py
arcade_serve/core/__init__.py
arcade_serve/core/auth.py
arcade_serve/core/base.py
arcade_serve/core/common.py
arcade_serve/core/components.py
arcade_serve/fastapi/__init__.py
arcade_serve/fastapi/auth.py
arcade_serve/fastapi/task_tracker.py
arcade_serve/fastapi/telemetry.py
arcade_serve/fastapi/worker.py
arcade_serve-3.2.1.dist-info/METADATA
arcade_serve-3.2.1.dist-info/WHEEL
arcade_serve-3.2.1.dist-info/RECORD
