Metadata-Version: 2.4
Name: arcade-serve
Version: 3.2.1
Summary: Arcade Serve - Serving infrastructure for Arcade tools and workers
Author-email: Arcade <dev@arcade.dev>
License: MIT
Classifier: Development Status :: 5 - Production/Stable
Classifier: Intended Audience :: Developers
Classifier: License :: OSI Approved :: MIT License
Classifier: Programming Language :: Python :: 3
Classifier: Programming Language :: Python :: 3.10
Classifier: Programming Language :: Python :: 3.11
Classifier: Programming Language :: Python :: 3.12
Classifier: Programming Language :: Python :: 3.13
Requires-Python: >=3.10
Requires-Dist: aiohttp<4.0.0,>=3.0.0
Requires-Dist: arcade-core<5.0.0,>=4.0.0
Requires-Dist: fastapi>=0.115.3
Requires-Dist: opentelemetry-exporter-otlp-proto-common==1.28.2
Requires-Dist: opentelemetry-exporter-otlp-proto-http==1.28.2
Requires-Dist: opentelemetry-instrumentation-aiohttp-client==0.49b2
Requires-Dist: opentelemetry-instrumentation-fastapi==0.49b2
Requires-Dist: opentelemetry-instrumentation-httpx==0.49b2
Requires-Dist: opentelemetry-instrumentation-requests==0.49b2
Requires-Dist: sse-starlette>=2.0.0
Requires-Dist: uvicorn>=0.30.0
Requires-Dist: watchfiles>=1.0.5
Provides-Extra: dev
Requires-Dist: mypy>=1.5.1; extra == 'dev'
Requires-Dist: pre-commit>=3.4.0; extra == 'dev'
Requires-Dist: pytest-asyncio>=0.23.7; extra == 'dev'
Requires-Dist: pytest-cov>=4.0.0; extra == 'dev'
Requires-Dist: pytest>=8.1.2; extra == 'dev'
